metacycle.py
metacycle-0.1.7.dist-info/METADATA
metacycle-0.1.7.dist-info/WHEEL
metacycle-0.1.7.dist-info/entry_points.txt
metacycle-0.1.7.dist-info/licenses/LICENSE
metacycle-0.1.7.dist-info/RECORD
