Metadata-Version: 2.4
Name: metacycle
Version: 0.1.7
Summary: Open-world cycling with bluetooth accessories in carla simulator.
License-File: LICENSE
Requires-Python: ~=3.10
Requires-Dist: bleak>=0.22.3
Requires-Dist: carla==0.9.15
Requires-Dist: numpy>=2.2.2
Requires-Dist: opencv-python>=4.11.0.86
Requires-Dist: pycycling>=0.4.1
Requires-Dist: pygame>=2.6.1
